Reviewable/__init__.py
Reviewable/admin.py
Reviewable/apps.py
Reviewable/models.py
Reviewable/urls.py
Reviewable/views.py
Reviewable/migrations/0001_initial.py
Reviewable/migrations/__init__.py
Reviewable/templates/Reviewable/__review_controls.html
Reviewable/templates/Reviewable/review_confirm_delete.html
Reviewable/templates/Reviewable/review_create.html
Reviewable/templates/Reviewable/review_detail.html
Reviewable/templates/Reviewable/review_list.html
Reviewable/templates/Reviewable/review_update.html
Reviewable/templatetags/__init__.py
Reviewable/templatetags/reviewable.py
django_reviewable-0.3.9.2.dist-info/DESCRIPTION.rst
django_reviewable-0.3.9.2.dist-info/METADATA
django_reviewable-0.3.9.2.dist-info/RECORD
django_reviewable-0.3.9.2.dist-info/WHEEL
django_reviewable-0.3.9.2.dist-info/metadata.json
django_reviewable-0.3.9.2.dist-info/top_level.txt
