Metadata-Version: 2.0
Name: django-reviewable
Version: 0.3.9.2
Summary: Simple, customizable reviews for any of your Django models
Home-page: https://github.com/jacobwindsor/django-reviewable
Author: Jacob Windsor
Author-email: jacob.windsor@ymail.com
License: MIT License
Platform: UNKNOWN
Classifier: Environment :: Web Environment
Classifier: Framework :: Django
Classifier: Framework :: Django :: 1.9
Classifier: Intended Audience :: Developers
Classifier: License :: OSI Approved :: MIT License
Classifier: Operating System :: OS Independent
Classifier: Programming Language :: Python
Classifier: Programming Language :: Python :: 3.5
Classifier: Topic :: Internet :: WWW/HTTP
Classifier: Topic :: Internet :: WWW/HTTP :: Dynamic Content
